openai_otel/__init__.py
openai_otel-0.1.0a3.dist-info/LICENSE
openai_otel-0.1.0a3.dist-info/METADATA
openai_otel-0.1.0a3.dist-info/WHEEL
openai_otel-0.1.0a3.dist-info/RECORD
