Metadata-Version: 2.1
Name: openai-otel
Version: 0.1.0a3
Summary: openai-otel is a library that automatically instrument your OpenAI python code using OpenTelemetry
License: MIT
Author: Jingkai He
Author-email: jingkai@hey.com
Requires-Python: >=3.10,<4.0
Classifier: License :: OSI Approved :: MIT License
Classifier: Programming Language :: Python :: 3
Classifier: Programming Language :: Python :: 3.10
Classifier: Programming Language :: Python :: 3.11
Classifier: Programming Language :: Python :: 3.12
Requires-Dist: openai (>=1.44.1,<2.0.0)
Requires-Dist: opentelemetry-api (>=1.27.0,<2.0.0)
Requires-Dist: opentelemetry-instrumentation (>=0.48b0,<0.49)
Requires-Dist: opentelemetry-sdk (>=1.27.0,<2.0.0)
